imagedominantcolour/__init__.py
imagedominantcolour/__version__.py
imagedominantcolour/dominantcolour.py
imagedominantcolour-1.0.2.dist-info/LICENSE
imagedominantcolour-1.0.2.dist-info/METADATA
imagedominantcolour-1.0.2.dist-info/WHEEL
imagedominantcolour-1.0.2.dist-info/top_level.txt
imagedominantcolour-1.0.2.dist-info/RECORD
