Metadata-Version: 2.1
Name: imagedominantcolour
Version: 1.0.2
Summary: Find dominant aka most common colour of any image.
Home-page: https://akamhy.github.io/imagedominantcolor/
Download-URL: https://github.com/demmenie/imagedominantcolour/archive/1.0.2.tar.gz
Author: Akash Mahanty and Chico Demmenie
Author-email: cdemmenie@gmail.com
License: MIT
Project-URL: Source, https://github.com/demmenie/imagedominantcolour
Project-URL: Tracker, https://github.com/demmenie/imagedominantcolour/issues
Keywords: Get dominant colours of image,imagedominantcolour,Extract dominant colours of an image using Python,Dominant colours,most prevalent colour,most dominant colours
Classifier: Development Status :: 5 - Production/Stable
Classifier: Intended Audience :: Developers
Classifier: Natural Language :: English
Classifier: License :: OSI Approved :: MIT License
Classifier: Programming Language :: Python
Classifier: Programming Language :: Python :: 3
Classifier: Programming Language :: Python :: 3.7
Classifier: Programming Language :: Python :: 3.8
Classifier: Programming Language :: Python :: 3.9
Classifier: Programming Language :: Python :: 3.10
Classifier: Programming Language :: Python :: 3.11
Classifier: Programming Language :: Python :: Implementation :: CPython
Requires-Python: >=3.7
License-File: LICENSE
Requires-Dist: Pillow
